biliupload/__init__.py
biliupload/cli.py
biliupload/config.json
biliupload/ioer.py
biliupload/controller/__init__.py
biliupload/controller/download_controller.py
biliupload/controller/upload_controller.py
biliupload/download/__init__.py
biliupload/download/bili_download.py
biliupload/login/__init__.py
biliupload/login/check_login.py
biliupload/login/login_bili.py
biliupload/login/logout_bili.py
biliupload/upload/__init__.py
biliupload/upload/bili_upload.py
biliupload/utils/__init__.py
biliupload/utils/get_ip_info.py
biliupload/utils/parse_cookies.py
biliupload/utils/parse_yaml.py
biliupload-0.0.4.dist-info/METADATA
biliupload-0.0.4.dist-info/WHEEL
biliupload-0.0.4.dist-info/entry_points.txt
biliupload-0.0.4.dist-info/licenses/LICENSE
biliupload-0.0.4.dist-info/RECORD
