Metadata-Version: 2.4
Name: biliupload
Version: 0.0.4
Summary: Login and upload videos to bilibili
Project-URL: Homepage, https://github.com/timerring/biliupload
Author: timerring
License: MIT License
License-File: LICENSE
Classifier: License :: OSI Approved :: MIT License
Classifier: Operating System :: OS Independent
Classifier: Programming Language :: Python :: 3
Requires-Python: >=3.10
Requires-Dist: pyyaml==6.0.2
Requires-Dist: qrcode==8.0
Requires-Dist: requests==2.32.3
